pyrender/interface.py
pyrender/tool.py
pyrender/http_service/__init__.py
pyrender/http_service/main.py
pyrender/http_service/routing.py
pyrender/http_service/service.py
pyrender/http_service/api/__init__.py
pyrender/http_service/api/view.py
pyrender/selenium_service/__init__.py
pyrender/selenium_service/main.py
web_render-0.1.3.dist-info/METADATA
web_render-0.1.3.dist-info/WHEEL
web_render-0.1.3.dist-info/top_level.txt
web_render-0.1.3.dist-info/RECORD
