Metadata-Version: 2.1
Name: web-render
Version: 0.1.3
Summary: Web sites render.
Home-page: 
Author: Andrey Plugin
Author-email: 9keepa@gmail.com
License: Apache 2.0
Requires-Python: >=3.8
Requires-Dist: Flask
Requires-Dist: selenium
Requires-Dist: selenium-stealth
Requires-Dist: webdriver-manager
Requires-Dist: waitress
